cupti/__init__.py
cupti/buffer_manager.cpython-310-x86_64-linux-gnu.so
cupti/callback_wrappers.cpython-310-x86_64-linux-gnu.so
cupti/cupti.cpython-310-x86_64-linux-gnu.so
cupti/cupti.pyi
cupti/cycupti.cpython-310-x86_64-linux-gnu.so
cupti/globals.cpython-310-x86_64-linux-gnu.so
cupti/utils.cpython-310-x86_64-linux-gnu.so
cupti/_internal/cupti.cpython-310-x86_64-linux-gnu.so
cupti/_internal/utils.cpython-310-x86_64-linux-gnu.so
cupti-python-samples/CuptiVectorAddDrv.py
cupti-python-samples/CuptiVectorAddNumba.py
cupti-python-samples/CuptiVectorAddNumbaCallback.py
cupti-python-samples/cupti_common.py
cupti-python-samples/cupyprof.py
cupti_python-13.0.1.dist-info/METADATA
cupti_python-13.0.1.dist-info/WHEEL
cupti_python-13.0.1.dist-info/top_level.txt
cupti_python-13.0.1.dist-info/RECORD
cupti_python-13.0.1.dist-info/licenses/LICENSE
