Metadata-Version: 2.4
Name: cupti-python
Version: 13.0.1
Summary: NVIDIA CUPTI Python Library
Author: NVIDIA Corporation
License: NVIDIA SOFTWARE LICENSE AGREEMENT
Project-URL: Documentation, https://docs.nvidia.com/cupti-python/13.0.1/index.html
Project-URL: License, https://docs.nvidia.com/cupti-python/13.0.1/nvidia-cupti-python-license.html
Classifier: Intended Audience :: Developers
Classifier: License :: Other/Proprietary License
Classifier: Programming Language :: Python
Classifier: Programming Language :: Python :: 3.9
Classifier: Programming Language :: Python :: 3.10
Classifier: Programming Language :: Python :: 3.11
Classifier: Programming Language :: Python :: 3.12
Classifier: Programming Language :: Python :: 3.13
Classifier: Environment :: GPU :: NVIDIA CUDA
Requires-Python: >=3.9
License-File: LICENSE
Requires-Dist: cuda-bindings~=13.0
Requires-Dist: numpy>=1.23
Requires-Dist: nvidia-cuda-cupti~=13.0
Dynamic: license-file
Dynamic: requires-python
